doublespace.abi3.so
doublespace-1.0.1.dist-info/METADATA
doublespace-1.0.1.dist-info/WHEEL
doublespace-1.0.1.dist-info/RECORD
