Metadata-Version: 2.4
Name: doublespace
Version: 1.0.1
Summary: Python extension for doublespace decompression
Keywords: Compression,Doublespace,libdeds
Author-Email: Armin Wolf <W_Armin@gmx.de>
License-Expression: GPL-2.0-or-later
Classifier: Development Status :: 5 - Production/Stable
Classifier: Environment :: Other Environment
Classifier: Intended Audience :: Developers
Classifier: Operating System :: POSIX
Classifier: Programming Language :: C
Classifier: Topic :: System :: Archiving :: Compression
Classifier: Topic :: Software Development :: Libraries
Project-URL: Repository, https://github.com/Wer-Wolf/doublespace
Project-URL: Bugtracker, https://github.com/Wer-Wolf/doublespace/issues
Requires-Python: >=3.12
